jupyterlab_local_browser/__init__.py
jupyterlab_local_browser/_version.py
jupyterlab_local_browser/config.py
jupyterlab_local_browser/handlers.py
jupyterlab_local_browser/public/index.html
jupyterlab_local_browser/public/styles.css
jupyterlab_local_browser-0.5.2.data/data/share/jupyter/labextensions/jupyterlab_local_browser/build_log.json
jupyterlab_local_browser-0.5.2.data/data/share/jupyter/labextensions/jupyterlab_local_browser/package.json
jupyterlab_local_browser-0.5.2.data/data/share/jupyter/labextensions/jupyterlab_local_browser/static/lib_index_js.10a0491e4ebc780d15fe.js
jupyterlab_local_browser-0.5.2.data/data/share/jupyter/labextensions/jupyterlab_local_browser/static/lib_index_js.10a0491e4ebc780d15fe.js.map
jupyterlab_local_browser-0.5.2.data/data/share/jupyter/labextensions/jupyterlab_local_browser/static/lib_index_js.35319085ca1b97ab0d6a.js
jupyterlab_local_browser-0.5.2.data/data/share/jupyter/labextensions/jupyterlab_local_browser/static/lib_index_js.35319085ca1b97ab0d6a.js.map
jupyterlab_local_browser-0.5.2.data/data/share/jupyter/labextensions/jupyterlab_local_browser/static/lib_index_js.41b9e7d4cf60f00fe679.js
jupyterlab_local_browser-0.5.2.data/data/share/jupyter/labextensions/jupyterlab_local_browser/static/lib_index_js.41b9e7d4cf60f00fe679.js.map
jupyterlab_local_browser-0.5.2.data/data/share/jupyter/labextensions/jupyterlab_local_browser/static/lib_index_js.b6a694fcf019446e4636.js
jupyterlab_local_browser-0.5.2.data/data/share/jupyter/labextensions/jupyterlab_local_browser/static/lib_index_js.b6a694fcf019446e4636.js.map
jupyterlab_local_browser-0.5.2.data/data/share/jupyter/labextensions/jupyterlab_local_browser/static/remoteEntry.09faa6acac3e5bad4226.js.map
jupyterlab_local_browser-0.5.2.data/data/share/jupyter/labextensions/jupyterlab_local_browser/static/remoteEntry.213bec2df119da4891d1.js.map
jupyterlab_local_browser-0.5.2.data/data/share/jupyter/labextensions/jupyterlab_local_browser/static/remoteEntry.22b76f2ceff3479199ae.js.map
jupyterlab_local_browser-0.5.2.dist-info/METADATA
jupyterlab_local_browser-0.5.2.dist-info/WHEEL
jupyterlab_local_browser-0.5.2.dist-info/licenses/LICENSE
jupyterlab_local_browser-0.5.2.dist-info/RECORD
