Metadata-Version: 2.1
Name: jupyterlab_local_browser
Version: 0.5.2
Summary: A JupyterLab local browser
Project-URL: Homepage, https://github.com/scmmmh/jupyterlab-local-browser
Project-URL: Bug Tracker, https://github.com/scmmmh/jupyterlab-local-browser/issues
Project-URL: Repository, https://github.com/scmmmh/jupyterlab-local-browser.git
Author-email: Mark Hall <mark.hall@open.ac.uk>
License: BSD 3-Clause License
License-File: LICENSE
Classifier: Framework :: Jupyter
Classifier: Framework :: Jupyter :: JupyterLab
Classifier: Framework :: Jupyter :: JupyterLab :: 3
Classifier: Framework :: Jupyter :: JupyterLab :: Extensions
Classifier: Framework :: Jupyter :: JupyterLab :: Extensions :: Prebuilt
Classifier: License :: OSI Approved :: BSD License
Classifier: Programming Language :: Python
Classifier: Programming Language :: Python :: 3
Classifier: Programming Language :: Python :: 3.8
Classifier: Programming Language :: Python :: 3.9
Classifier: Programming Language :: Python :: 3.10
Classifier: Programming Language :: Python :: 3.11
Requires-Python: >=3.8
Requires-Dist: jupyter-server-proxy
Requires-Dist: jupyterlab<4,>=3.0.0
Requires-Dist: psutil
